smartbreaks/__init__.py
smartbreaks/smartbreaks.py
markdown_smartbreaks-1.0.0.dist-info/LICENSE
markdown_smartbreaks-1.0.0.dist-info/METADATA
markdown_smartbreaks-1.0.0.dist-info/WHEEL
markdown_smartbreaks-1.0.0.dist-info/top_level.txt
markdown_smartbreaks-1.0.0.dist-info/RECORD
